urlshort/helpers.py
urlshort/models.py
urlshort/urls.py
urlshort/utils.py
urlshort/views.py
urlshort/migrations/0001_initial.py
urlshort/migrations/__init__.py
ldc_urlshort-0.0.2.dist-info/METADATA
ldc_urlshort-0.0.2.dist-info/WHEEL
ldc_urlshort-0.0.2.dist-info/top_level.txt
ldc_urlshort-0.0.2.dist-info/RECORD
