Metadata-Version: 2.1
Name: ldc-urlshort
Version: 0.0.2
Summary: A simple package to shorten URLs
Author: Pratik Kumar
Author-email: pratik.kumar@lendenclub.com
Classifier: Intended Audience :: Developers
Classifier: Programming Language :: Python :: 3
Classifier: Topic :: Utilities
Requires-Dist: Django >=3.2.16
Requires-Dist: djangorestframework >=3.14.0
Requires-Dist: python-dateutil
